LICENSE
README.md
setup.py
asyncjson/__init__.py
asyncjson/_encoder.py
asyncjson/_encoder2.py
asyncjson/encoder.py
asyncjson.egg-info/PKG-INFO
asyncjson.egg-info/SOURCES.txt
asyncjson.egg-info/dependency_links.txt
asyncjson.egg-info/top_level.txt