Metadata-Version: 2.1
Name: asyncjson
Version: 0.0.1
Summary: Asynchronous json library with support of nested awaitable objects in data
Home-page: https://github.com/bdragon300/asyncjson
Author: Igor Derkach
Author-email: gosha753951@gmail.com
License: Apache 2.0
Platform: UNKNOWN
Classifier: Programming Language :: Python :: 3.6
Classifier: Programming Language :: Python :: 3.7
Classifier: Programming Language :: Python :: 3.8
Classifier: Programming Language :: Python :: 3.9
Classifier: Programming Language :: Python :: 3.10
Classifier: Development Status :: 3 - Alpha
Classifier: License :: OSI Approved :: Apache Software License
Classifier: Topic :: Software Development :: Libraries
Requires-Python: >=3.6
License-File: LICENSE
